_examples/__init__.py
cryptocompsdk/__init__.py
cryptocompsdk/config.py
cryptocompsdk/logger.py
cryptocompsdk/main.py
cryptocompsdk/request.py
cryptocompsdk/response.py
cryptocompsdk/urls.py
cryptocompsdk/blockchain/__init__.py
cryptocompsdk/blockchain/available/__init__.py
cryptocompsdk/blockchain/available/api.py
cryptocompsdk/blockchain/available/parse.py
cryptocompsdk/blockchain/history/__init__.py
cryptocompsdk/blockchain/history/api.py
cryptocompsdk/blockchain/history/parse.py
cryptocompsdk/coins/__init__.py
cryptocompsdk/coins/api.py
cryptocompsdk/coins/parse.py
cryptocompsdk/exchanges/__init__.py
cryptocompsdk/exchanges/info/__init__.py
cryptocompsdk/exchanges/info/api.py
cryptocompsdk/exchanges/info/parse.py
cryptocompsdk/exchanges/symbols/__init__.py
cryptocompsdk/exchanges/symbols/api.py
cryptocompsdk/exchanges/symbols/parse.py
cryptocompsdk/general/__init__.py
cryptocompsdk/general/parse.py
cryptocompsdk/history/__init__.py
cryptocompsdk/history/api.py
cryptocompsdk/history/parse.py
cryptocompsdk/news/__init__.py
cryptocompsdk/news/api.py
cryptocompsdk/news/parse.py
cryptocompsdk/social/__init__.py
cryptocompsdk/social/current/__init__.py
cryptocompsdk/social/current/api.py
cryptocompsdk/social/current/parse.py
cryptocompsdk/social/history/__init__.py
cryptocompsdk/social/history/api.py
cryptocompsdk/social/history/parse.py
examples/__init__.py
tests/__init__.py
tests/test_cryptocompsdk.py
cryptocompsdk-0.4.4.dist-info/LICENSE.md
cryptocompsdk-0.4.4.dist-info/METADATA
cryptocompsdk-0.4.4.dist-info/WHEEL
cryptocompsdk-0.4.4.dist-info/entry_points.txt
cryptocompsdk-0.4.4.dist-info/top_level.txt
cryptocompsdk-0.4.4.dist-info/RECORD
