Metadata-Version: 2.1
Name: cryptocompsdk
Version: 0.4.4
Summary: Python SDK for CryptoCompare Personal API
Home-page: https://github.com/nickderobertis/cryptocompare-py
Author: Nick DeRobertis
Author-email: whoopnip@gmail.com
License: MIT
Project-URL: Code, https://github.com/nickderobertis/cryptocompare-py
Project-URL: Documentation, https://nickderobertis.github.io/cryptocompare-py
Platform: UNKNOWN
Classifier: Development Status :: 3 - Alpha
Classifier: Intended Audience :: Developers
Classifier: Programming Language :: Python :: 3.7
Requires-Dist: requests
Requires-Dist: pandas
